adder.t.v
// Adder testbench
`timescale 1 ns / 1 ps
`include "adder.v"


module test4BitFullAdder();
    reg [3:0] addr0, addr1;
    wire [3:0] sum;
    wire carryout, overflow;

    FullAdder4bit adder(.sum(sum), .carryout(carryout), .overflow(overflow), .a(addr0), .b(addr1));

    initial begin

    $dumpfile("4bitadder.vcd");
    $dumpvars();

    $display("A3 A2 A1 A0 B3 B2 B1 B0 | Overflow | Expected Overflow  | Sum3 Sum2 Sum1 Sum0 | Sum Should Be | Carry Out | Expected Carry Out");

    // Cases 1-4 Extremes
    addr0[0]=0;addr0[1]=0;addr0[2]=0;addr0[3]=0;addr1[0]=0;addr1[1]=0;addr1[2]=0;addr1[3]=0; #1000
    $display("%b  %b  %b  %b  %b  %b  %b  %b  | %b        | 0                  | %b    %b    %b    %b    |      0000     |     %b     | 0 ", addr0[3], addr0[2], addr0[1], addr0[0],addr1[3], addr1[2], addr1[1], addr1[0], overflow, sum[3], sum[2], sum[1], sum[0], carryout );
    addr0[0]=1;addr0[1]=1;addr0[2]=1;addr0[3]=1;addr1[0]=1;addr1[1]=1;addr1[2]=1;addr1[3]=1; #1000
    $display("%b  %b  %b  %b  %b  %b  %b  %b  | %b        | 0                  | %b    %b    %b    %b    |      1110     |     %b     | 1 ", addr0[3], addr0[2], addr0[1], addr0[0],addr1[3], addr1[2], addr1[1], addr1[0], overflow, sum[3], sum[2], sum[1], sum[0], carryout );
    addr0[0]=1;addr0[1]=1;addr0[2]=0;addr0[3]=0;addr1[0]=1;addr1[1]=1;addr1[2]=0;addr1[3]=0; #1000
    $display("%b  %b  %b  %b  %b  %b  %b  %b  | %b        | 0                  | %b    %b    %b    %b    |      0110     |     %b     | 0 ", addr0[3], addr0[2], addr0[1], addr0[0],addr1[3], addr1[2], addr1[1], addr1[0], overflow, sum[3], sum[2], sum[1], sum[0], carryout );
    addr0[0]=0;addr0[1]=0;addr0[2]=1;addr0[3]=1;addr1[0]=0;addr1[1]=0;addr1[2]=1;addr1[3]=1; #1000
    $display("%b  %b  %b  %b  %b  %b  %b  %b  | %b        | 0                  | %b    %b    %b    %b    |      1000     |     %b     | 1 ", addr0[3], addr0[2], addr0[1], addr0[0],addr1[3], addr1[2], addr1[1], addr1[0], overflow, sum[3], sum[2], sum[1], sum[0], carryout );

    // Cases 5-6: No Carry Out
    addr0[3]=0;addr0[2]=0;addr0[1]=0;addr0[0]=1;addr1[3]=0;addr1[2]=1;addr1[1]=0;addr1[0]=0; #1000
    $display("%b  %b  %b  %b  %b  %b  %b  %b  | %b        | 0                  | %b    %b    %b    %b    |      0101     |     %b     | 0 ", addr0[3], addr0[2], addr0[1], addr0[0],addr1[3], addr1[2], addr1[1], addr1[0], overflow, sum[3], sum[2], sum[1], sum[0], carryout );
    addr0[3]=0;addr0[2]=1;addr0[1]=0;addr0[0]=1;addr1[3]=1;addr1[2]=0;addr1[1]=1;addr1[0]=0; #1000
    $display("%b  %b  %b  %b  %b  %b  %b  %b  | %b        | 0                  | %b    %b    %b    %b    |      1111     |     %b     | 0 ", addr0[3], addr0[2], addr0[1], addr0[0],addr1[3], addr1[2], addr1[1], addr1[0], overflow, sum[3], sum[2], sum[1], sum[0], carryout );
    
    // Cases 7-10: With Carry Out
    addr0[3]=0;addr0[2]=1;addr0[1]=0;addr0[0]=1;addr1[3]=0;addr1[2]=1;addr1[1]=0;addr1[0]=1; #1000
    $display("%b  %b  %b  %b  %b  %b  %b  %b  | %b        | 1                  | %b    %b    %b    %b    |      1010     |     %b     | 0 ", addr0[3], addr0[2], addr0[1], addr0[0],addr1[3], addr1[2], addr1[1], addr1[0], overflow, sum[3], sum[2], sum[1], sum[0], carryout );
    addr0[3]=1;addr0[2]=1;addr0[1]=0;addr0[0]=1;addr1[3]=0;addr1[2]=0;addr1[1]=1;addr1[0]=1; #1000
    $display("%b  %b  %b  %b  %b  %b  %b  %b  | %b        | 0                  | %b    %b    %b    %b    |      0000     |     %b     | 1 ", addr0[3], addr0[2], addr0[1], addr0[0],addr1[3], addr1[2], addr1[1], addr1[0], overflow, sum[3], sum[2], sum[1], sum[0], carryout );
    addr0[3]=1;addr0[2]=0;addr0[1]=1;addr0[0]=0;addr1[3]=1;addr1[2]=1;addr1[1]=0;addr1[0]=1; #1000
    $display("%b  %b  %b  %b  %b  %b  %b  %b  | %b        | 1                  | %b    %b    %b    %b    |      0111     |     %b     | 1 ", addr0[3], addr0[2], addr0[1], addr0[0],addr1[3], addr1[2], addr1[1], addr1[0], overflow, sum[3], sum[2], sum[1], sum[0], carryout );
    addr0[3]=1;addr0[2]=0;addr0[1]=1;addr0[0]=0;addr1[3]=1;addr1[2]=1;addr1[1]=0;addr1[0]=0; #1000
    $display("%b  %b  %b  %b  %b  %b  %b  %b  | %b        | 1                  | %b    %b    %b    %b    |      0110     |     %b     | 1 ", addr0[3], addr0[2], addr0[1], addr0[0],addr1[3], addr1[2], addr1[1], addr1[0], overflow, sum[3], sum[2], sum[1], sum[0], carryout );

    // Cases 11-16
    addr0[3]=0;addr0[2]=1;addr0[1]=0;addr0[0]=0;addr1[3]=1;addr1[2]=1;addr1[1]=0;addr1[0]=1; #1000
    $display("%b  %b  %b  %b  %b  %b  %b  %b  | %b        | 0                  | %b    %b    %b    %b    |      0001     |     %b     | 1 ", addr0[3], addr0[2], addr0[1], addr0[0],addr1[3], addr1[2], addr1[1], addr1[0], overflow, sum[3], sum[2], sum[1], sum[0], carryout );
    addr0[3]=1;addr0[2]=0;addr0[1]=0;addr0[0]=1;addr1[3]=0;addr1[2]=1;addr1[1]=1;addr1[0]=0; #1000
    $display("%b  %b  %b  %b  %b  %b  %b  %b  | %b        | 0                  | %b    %b    %b    %b    |      1111     |     %b     | 0 ", addr0[3], addr0[2], addr0[1], addr0[0],addr1[3], addr1[2], addr1[1], addr1[0], overflow, sum[3], sum[2], sum[1], sum[0], carryout );
    addr0[3]=1;addr0[2]=1;addr0[1]=0;addr0[0]=1;addr1[3]=0;addr1[2]=1;addr1[1]=1;addr1[0]=1; #1000
    $display("%b  %b  %b  %b  %b  %b  %b  %b  | %b        | 0                  | %b    %b    %b    %b    |      0100     |     %b     | 1 ", addr0[3], addr0[2], addr0[1], addr0[0],addr1[3], addr1[2], addr1[1], addr1[0], overflow, sum[3], sum[2], sum[1], sum[0], carryout );
    addr0[3]=0;addr0[2]=1;addr0[1]=1;addr0[0]=1;addr1[3]=1;addr1[2]=0;addr1[1]=0;addr1[0]=1; #1000
    $display("%b  %b  %b  %b  %b  %b  %b  %b  | %b        | 0                  | %b    %b    %b    %b    |      0000     |     %b     | 1 ", addr0[3], addr0[2], addr0[1], addr0[0],addr1[3], addr1[2], addr1[1], addr1[0], overflow, sum[3], sum[2], sum[1], sum[0], carryout );
    addr0[3]=0;addr0[2]=0;addr0[1]=0;addr0[0]=1;addr1[3]=1;addr1[2]=1;addr1[1]=1;addr1[0]=1; #1000
    $display("%b  %b  %b  %b  %b  %b  %b  %b  | %b        | 0                  | %b    %b    %b    %b    |      0000     |     %b     | 1 ", addr0[3], addr0[2], addr0[1], addr0[0],addr1[3], addr1[2], addr1[1], addr1[0], overflow, sum[3], sum[2], sum[1], sum[0], carryout );
    addr0[3]=1;addr0[2]=0;addr0[1]=1;addr0[0]=1;addr1[3]=1;addr1[2]=1;addr1[1]=0;addr1[0]=1; #1000
    $display("%b  %b  %b  %b  %b  %b  %b  %b  | %b        | 0                  | %b    %b    %b    %b    |      1000     |     %b     | 1 ", addr0[3], addr0[2], addr0[1], addr0[0],addr1[3], addr1[2], addr1[1], addr1[0], overflow, sum[3], sum[2], sum[1], sum[0], carryout );
    
    
    
    
    




    $finish();

    end

endmodule

adder.v
// Adder circuit

`define AND and #50
`define OR or #50
`define NOT not #50
`define XOR xor #50

module behavioralFullAdder
(
    output sum,
    output carryout,
    input a,
    input b,
    input carryin
);
    // Uses concatenation operator and built-in '+'
    assign {carryout, sum}=a+b+carryin;
endmodule

module structuralFullAdder
(
    output sum,
    output carryout,
    input a,
    input b,
    input carryin

);

 wire AxorB, AxorBxorC, AxorBC, AB;

 `XOR xorGate(AxorB, a, b);
 `XOR xorGate(sum, AxorB, carryin);
 `AND andGate(AB, a, b);
 `AND andGate(AxorBC, carryin, AxorB);
 `OR orGate( carryout, AB, AxorBC);



endmodule


module FullAdder4bit
(
  output[3:0] sum,  // 2's complement sum of a and b
  output carryout,  // Carry out of the summation of a and b
  output overflow,  // True if the calculation resulted in an overflow
  input[3:0] a,     // First operand in 2's complement format
  input[3:0] b      // Second operand in 2's complement format
);
    // Your Code Here

    //reg a, b, carryin;
    wire carryout0, carryout1, carryout2;

    structuralFullAdder adder0(sum[0], carryout0, a[0], b[0], 1'b0);
    structuralFullAdder adder1(sum[1], carryout1, a[1], b[1], carryout0);
    structuralFullAdder adder2(sum[2], carryout2, a[2], b[2], carryout1);
    structuralFullAdder adder3(sum[3], carryout, a[3], b[3], carryout2);

    // Overflow is the value of carryout, so we use an and gate
    `XOR xorGate(overflow, carryout, carryout2);


endmodule

4bitadder.vcd
$date
	Mon Sep 24 22:07:39 2018
$end
$version
	Icarus Verilog
$end
$timescale
	1ps
$end
$scope module behavioralFullAdder $end
$var wire 1 ! a $end
$var wire 1 " b $end
$var wire 1 # carryin $end
$var wire 1 $ sum $end
$var wire 1 % carryout $end
$upscope $end
$scope module test4BitFullAdder $end
$var wire 4 & sum [3:0] $end
$var wire 1 ' overflow $end
$var wire 1 ( carryout $end
$var reg 4 ) addr0 [3:0] $end
$var reg 4 * addr1 [3:0] $end
$scope module adder $end
$var wire 4 + a [3:0] $end
$var wire 4 , b [3:0] $end
$var wire 1 ' overflow $end
$var wire 4 - sum [3:0] $end
$var wire 1 . carryout2 $end
$var wire 1 / carryout1 $end
$var wire 1 0 carryout0 $end
$var wire 1 ( carryout $end
$scope module adder0 $end
$var wire 1 1 AB $end
$var wire 1 2 AxorB $end
$var wire 1 3 AxorBC $end
$var wire 1 4 a $end
$var wire 1 5 b $end
$var wire 1 6 carryin $end
$var wire 1 0 carryout $end
$var wire 1 7 sum $end
$upscope $end
$scope module adder1 $end
$var wire 1 8 AB $end
$var wire 1 9 AxorB $end
$var wire 1 : AxorBC $end
$var wire 1 ; a $end
$var wire 1 < b $end
$var wire 1 0 carryin $end
$var wire 1 / carryout $end
$var wire 1 = sum $end
$upscope $end
$scope module adder2 $end
$var wire 1 > AB $end
$var wire 1 ? AxorB $end
$var wire 1 @ AxorBC $end
$var wire 1 A a $end
$var wire 1 B b $end
$var wire 1 / carryin $end
$var wire 1 . carryout $end
$var wire 1 C sum $end
$upscope $end
$scope module adder3 $end
$var wire 1 D AB $end
$var wire 1 E AxorB $end
$var wire 1 F AxorBC $end
$var wire 1 G a $end
$var wire 1 H b $end
$var wire 1 . carryin $end
$var wire 1 ( carryout $end
$var wire 1 I sum $end
$upscope $end
$upscope $end
$upscope $end
$enddefinitions $end
#0
$dumpvars
xI
0H
0G
xF
xE
xD
xC
0B
0A
x@
x?
x>
x=
0<
0;
x:
x9
x8
x7
06
05
04
x3
x2
x1
x0
x/
x.
bx -
b0 ,
b0 +
b0 *
b0 )
x(
x'
bx &
x%
x$
z#
z"
z!
$end
#50000
0E
0D
0?
0>
09
08
02
01
03
#100000
0F
0@
0:
bx0 &
bx0 -
07
00
#150000
0(
0.
0/
bx00 &
bx00 -
0=
#200000
0I
0'
b0 &
b0 -
0C
#1000000
1H
1B
1<
15
1G
1A
1;
14
b1111 *
b1111 ,
b1111 )
b1111 +
#1050000
1D
1>
18
11
#1100000
1(
1.
1/
10
#1150000
1I
1C
b1110 &
b1110 -
1=
#2000000
0H
0B
0G
0A
b11 *
b11 ,
b11 )
b11 +
#2050000
0D
0>
#2100000
0(
0.
#2150000
b110 &
b110 -
0I
#3000000
1H
1B
0<
05
1G
1A
0;
04
b1100 *
b1100 ,
b1100 )
b1100 +
#3050000
1D
1>
08
01
#3100000
1(
1.
0/
00
#3150000
1I
0C
b1000 &
b1000 -
0=
#4000000
0H
14
0A
0G
b100 *
b100 ,
b1 )
b1 +
#4050000
12
1?
0>
0D
#4100000
17
b1101 &
b1101 -
1C
0.
0(
#4150000
b101 &
b101 -
0I
#5000000
1<
0B
1H
1A
b1010 *
b1010 ,
b101 )
b101 +
#5050000
19
1E
#5100000
1=
b1111 &
b1111 -
1I
#6000000
15
0<
1B
0H
b101 *
b101 ,
#6050000
02
11
09
0?
1>
0E
#6100000
07
10
0=
0C
1.
b0 &
b0 -
0I
#6150000
1=
b1010 &
b1010 -
1I
1'
#7000000
1<
0B
1G
b11 *
b11 ,
b1101 )
b1101 +
#7050000
19
1?
0>
1E
#7100000
0=
1:
1C
0.
b100 &
b100 -
0I
1F
#7150000
1/
b1100 &
b1100 -
1I
0F
0'
1(
#7200000
b1000 &
b1000 -
0C
1@
0(
1'
#7250000
1.
0'
#7300000
b0 &
b0 -
0I
1F
1'
#7350000
1(
#7400000
0'
#8000000
0<
1B
1H
04
1;
0A
b1101 *
b1101 ,
b1010 )
b1010 +
#8050000
0E
1D
12
01
#8100000
1I
0F
b1001 &
b1001 -
17
00
#8150000
b1011 &
b1011 -
1=
0:
#8200000
0/
#8250000
b1111 &
b1111 -
1C
0@
#8300000
0.
#8350000
b111 &
b111 -
0I
1'
#9000000
05
b1100 *
b1100 ,
#9050000
02
#9100000
b110 &
b110 -
07
#10000000
15
0;
1A
0G
b1101 *
b1101 ,
b100 )
b100 +
#10050000
12
09
0?
1>
1E
0D
#10100000
17
0=
0C
1.
b1001 &
b1001 -
1I
0(
#10150000
b1 &
b1 -
0I
1F
#10200000
1(
#10250000
0'
#11000000
05
1<
0H
14
0A
1G
b110 *
b110 ,
b1001 )
b1001 +
#11050000
19
1?
0>
#11100000
1=
b111 &
b111 -
1C
0.
#11150000
b1111 &
b1111 -
1I
0F
1'
#11200000
0(
#11250000
0'
#12000000
15
1A
b111 *
b111 ,
b1101 )
b1101 +
#12050000
02
11
0?
1>
#12100000
07
10
b1010 &
b1010 -
0C
1.
#12150000
0=
1:
b0 &
b0 -
0I
1F
1'
#12200000
1/
1(
#12250000
b100 &
b100 -
1C
0'
#13000000
0<
0B
1H
1;
0G
b1001 *
b1001 ,
b111 )
b111 +
#13050000
1?
0>
#13100000
b0 &
b0 -
0C
1@
0.
#13150000
1.
b1000 &
b1000 -
1I
0F
1'
#13200000
b0 &
b0 -
0I
1F
0'
0(
#13250000
1(
1'
#13300000
0'
#14000000
1<
1B
0;
0A
b1111 *
b1111 ,
b1 )
b1 +
#15000000
0<
1;
1G
b1101 *
b1101 ,
b1011 )
b1011 +
#15050000
0E
1D
#15100000
b1000 &
b1000 -
1I
0F
